pythoff/__init__.py
pythoff/_pep695.py
pythoff/py.typed
pythoff-0.1.0.dist-info/METADATA
pythoff-0.1.0.dist-info/WHEEL
pythoff-0.1.0.dist-info/entry_points.txt
pythoff-0.1.0.dist-info/licenses/LICENSE
pythoff-0.1.0.dist-info/RECORD
