Metadata-Version: 2.3
Name: pythoff
Version: 0.1.0
Summary: Python 3.12+ stub backporter
Project-URL: Repository, https://github.com/jorenham/pythoff
Project-URL: Documentation, https://github.com/jorenham/pythoff?tab=readme-ov-file#mainpy
Project-URL: Issues, https://github.com/jorenham/pythoff/issues
Project-URL: Changelog, https://github.com/jorenham/pythoff/releases
Project-URL: Funding, https://github.com/sponsors/jorenham
Author-email: Joren Hammudoglu <jhammudoglu@gmail.com>
License-Expression: BSD-3-Clause
License-File: LICENSE
Classifier: Development Status :: 3 - Alpha
Classifier: Intended Audience :: Developers
Classifier: License :: OSI Approved :: BSD License
Classifier: Natural Language :: English
Classifier: Operating System :: OS Independent
Classifier: Programming Language :: Python :: 3
Classifier: Programming Language :: Python :: 3.12
Classifier: Programming Language :: Python :: 3.13
Classifier: Topic :: Software Development :: Code Generators
Classifier: Topic :: Software Development :: Compilers
Classifier: Typing :: Typed
Requires-Python: >=3.12
Requires-Dist: libcst<2,>=1.4.0
Requires-Dist: mainpy<2,>=1.4.0
